ryo_iso/__init__.py
ryo_iso/__main__.py
ryo_iso/cli.py
ryo_iso/config.py
ryo_iso/utils.py
ryo_iso/__pycache__/__init__.cpython-36.pyc
ryo_iso/__pycache__/cli.cpython-36.pyc
ryo_iso/__pycache__/config.cpython-36.pyc
ryo_iso/__pycache__/utils.cpython-36.pyc
ryo_iso/data/__init__.py
ryo_iso/data/config.yml
ryo_iso/data/iso.yml
ryo_iso/data/iso_base.yml
ryo_iso/data/modinfo
ryo_iso/data/uname
ryo_iso/data/__pycache__/__init__.cpython-36.pyc
ryo_iso/tasks/__init__.py
ryo_iso/tasks/init.py
ryo_iso/tasks/main.py
ryo_iso/tasks/__pycache__/__init__.cpython-36.pyc
ryo_iso/tasks/__pycache__/init.cpython-36.pyc
ryo_iso/tasks/__pycache__/main.cpython-36.pyc
tests/__init__.py
tests/conftest.py
tests/test_10_init.py
tests/test_40_hash_version.py
ryo_iso-0.1.7.dist-info/LICENSE-APACHE
ryo_iso-0.1.7.dist-info/LICENSE-MIT
ryo_iso-0.1.7.dist-info/METADATA
ryo_iso-0.1.7.dist-info/WHEEL
ryo_iso-0.1.7.dist-info/entry_points.txt
ryo_iso-0.1.7.dist-info/top_level.txt
ryo_iso-0.1.7.dist-info/RECORD
