Metadata-Version: 2.1
Name: ryo-iso
Version: 0.1.7
Home-page: https://git.sr.ht/~lucidone/ryo-iso
Author: HXR
Author-email: code@hxr.io
Maintainer: HXR
Maintainer-email: code@hxr.io
License: MIT/Apache-2.0
Classifier: Development Status :: 4 - Beta
Classifier: Intended Audience :: Developers
Classifier: License :: OSI Approved :: MIT License
Classifier: License :: OSI Approved :: Apache Software License
Classifier: Natural Language :: English
Classifier: Operating System :: OS Independent
Classifier: Programming Language :: Python :: 3.8
Classifier: Programming Language :: Python :: Implementation :: CPython
Classifier: Programming Language :: Python :: Implementation :: PyPy
License-File: LICENSE-APACHE
License-File: LICENSE-MIT
Requires-Dist: appdirs
Requires-Dist: loguru
Requires-Dist: pyyaml
Requires-Dist: requests
Requires-Dist: delegator.py
Requires-Dist: doit
Requires-Dist: importlib-resources
Requires-Dist: tqdm
